pype4/__init__.py
pype4/build_helpers.py
pype4/csv_helpers.py
pype4/fargs.py
pype4/flask_helpers.py
pype4/func_helpers.py
pype4/helpers.py
pype4/loaders.py
pype4/macros.py
pype4/nodes.py
pype4/numpy_helpers.py
pype4/string_helpers.py
pype4/time_helpers.py
pype4/trees.py
pype4/type_checking.py
pype4/vals.py
python_pype_lang_4-4.0.6.dist-info/licenses/LICENSE.txt
python_pype_lang_4-4.0.6.dist-info/METADATA
python_pype_lang_4-4.0.6.dist-info/WHEEL
python_pype_lang_4-4.0.6.dist-info/top_level.txt
python_pype_lang_4-4.0.6.dist-info/RECORD
