Metadata-Version: 2.4
Name: python-pype-lang-4
Version: 4.0.6
Summary: Version 4 of pype, a Python-integrated functional programming language - Provides easy-to-use pseudo-macros for common functional programming tasks such as maps, reduces, filters, conditionals, dictionary manipulations, and list manipulations..
Home-page: https://github.com/bbbdragon-pype4/python-pype-lang-4.git
Author: Bennett Charles Bullock
Author-email: bennettbullock94@gmail.com
License: MIT
Keywords: functional programming map reduce filter lambda conditional
Classifier: License :: OSI Approved :: MIT License
Classifier: Programming Language :: Python :: 3.13
Classifier: Operating System :: OS Independent
License-File: LICENSE.txt
Requires-Dist: cython
Requires-Dist: numpy
Requires-Dist: chardet
Requires-Dist: colorama
Requires-Dist: astpretty
Requires-Dist: mmh3
Requires-Dist: requests
Requires-Dist: flask
Requires-Dist: twine
Requires-Dist: python-dateutil
Dynamic: author
Dynamic: author-email
Dynamic: classifier
Dynamic: home-page
Dynamic: keywords
Dynamic: license
Dynamic: license-file
Dynamic: requires-dist
Dynamic: summary
